hi_sourcing/__init__.py
hi_sourcing/hi_sourcing.py
hi_sourcing-0.0.13.dist-info/LICENSE
hi_sourcing-0.0.13.dist-info/METADATA
hi_sourcing-0.0.13.dist-info/WHEEL
hi_sourcing-0.0.13.dist-info/top_level.txt
hi_sourcing-0.0.13.dist-info/RECORD
